riboseq_mcp/__init__.py
riboseq_mcp/api_client.py
riboseq_mcp/server.py
rdp_mcp-0.2.0.dist-info/METADATA
rdp_mcp-0.2.0.dist-info/WHEEL
rdp_mcp-0.2.0.dist-info/entry_points.txt
rdp_mcp-0.2.0.dist-info/licenses/LICENSE
rdp_mcp-0.2.0.dist-info/RECORD
