Metadata-Version: 2.4
Name: RDP-MCP
Version: 0.2.0
Summary: MCP server for querying the RiboSeq.Org Data Portal - access ribosome profiling data through Claude and other LLMs
Project-URL: Homepage, https://rdp.ucc.ie
Project-URL: Repository, https://github.com/RiboSeqOrg/RiboSeqOrg-DataPortal
Project-URL: Documentation, https://rdp.ucc.ie/about
Author-email: "RiboSeq.Org" <riboseq@riboseq.org>
License: MIT
License-File: LICENSE
Keywords: ai,bioinformatics,claude,genomics,llm,mcp,rdp,riboseq,ribosome-profiling
Classifier: Development Status :: 4 - Beta
Classifier: Intended Audience :: Science/Research
Classifier: License :: OSI Approved :: MIT License
Classifier: Programming Language :: Python :: 3
Classifier: Programming Language :: Python :: 3.10
Classifier: Programming Language :: Python :: 3.11
Classifier: Programming Language :: Python :: 3.12
Classifier: Programming Language :: Python :: 3.13
Classifier: Topic :: Scientific/Engineering :: Bio-Informatics
Requires-Python: >=3.10
Requires-Dist: httpx>=0.27.0
Requires-Dist: mcp>=0.9.0
